my_text_summary_lib/__init__.py
my_text_summary_lib/my_text_summary_lib.py
my_text_summary_lib-0.2.0.dist-info/METADATA
my_text_summary_lib-0.2.0.dist-info/WHEEL
my_text_summary_lib-0.2.0.dist-info/RECORD
