Metadata-Version: 2.1
Name: my-text-summary-lib
Version: 0.2.0
Summary: 
Author: Your Name
Author-email: you@example.com
Requires-Python: >=3.12.1,<4.0.0
Classifier: Programming Language :: Python :: 3
Requires-Dist: nltk (>=3.6.3,<4.0.0)
Requires-Dist: pandas (>=2.1.4,<3.0.0)
Requires-Dist: scipy (>=1.11.4,<2.0.0)
